surface_crns/SurfaceCRNQueueSimulator.py
surface_crns/__init__.py
surface_crns/constants.py
surface_crns/generate_random_colors.py
surface_crns/ordered_dict.py
surface_crns/pygbutton.py
surface_crns/random_color.py
surface_crns/random_color_list.txt
surface_crns/assets/camera.png
surface_crns/assets/camera_green.png
surface_crns/assets/camera_yellow.png
surface_crns/base/__init__.py
surface_crns/base/node.py
surface_crns/base/transition_rule.py
surface_crns/models/__init__.py
surface_crns/models/emulated_grid.py
surface_crns/models/grids.py
surface_crns/options/__init__.py
surface_crns/options/option_processor.py
surface_crns/profiling/__init__.py
surface_crns/profiling/grid_timing.py
surface_crns/profiling/timing.py
surface_crns/readers/__init__.py
surface_crns/readers/colormap_readers.py
surface_crns/readers/grid_state_readers.py
surface_crns/readers/manifest_readers.py
surface_crns/readers/statements.py
surface_crns/readers/totalistic_readers.py
surface_crns/readers/transition_readers.py
surface_crns/simulators/__init__.py
surface_crns/simulators/event.py
surface_crns/simulators/event_history.py
surface_crns/simulators/queue_simulator.py
surface_crns/simulators/queue_simulator_eager.py
surface_crns/simulators/synchronous_simulator.py
surface_crns/views/__init__.py
surface_crns/views/grid_display.py
surface_crns/views/legend_display.py
surface_crns/views/text_display.py
surface_crns/views/time_display.py
surface_crns-1.2.1.dist-info/LICENSE
surface_crns-1.2.1.dist-info/METADATA
surface_crns-1.2.1.dist-info/WHEEL
surface_crns-1.2.1.dist-info/entry_points.txt
surface_crns-1.2.1.dist-info/top_level.txt
surface_crns-1.2.1.dist-info/RECORD
