Metadata-Version: 2.1
Name: surface-crns
Version: 1.2.1
Summary: Simulation of chemical reaction networks (CRNs) on a surface
Home-page: https://github.com/sclamons/surface_crns
Author: Samuel Clamons
Author-email: sclamons@gmail.com
License: MIT
Keywords: mathematics surface-chemistry cellular-automata
Platform: UNKNOWN
Classifier: Development Status :: 5 - Production/Stable
Classifier: Intended Audience :: Science/Research
Classifier: Topic :: Scientific/Engineering :: Mathematics
Classifier: Topic :: Scientific/Engineering :: Chemistry
Classifier: Topic :: Scientific/Engineering :: Visualization
Classifier: License :: OSI Approved :: MIT License
Classifier: Programming Language :: Python :: 3
Classifier: Programming Language :: Python :: 3.7
Classifier: Programming Language :: Python :: 3.8
Classifier: Operating System :: OS Independent
Classifier: Natural Language :: English
License-File: LICENSE
